{
  "target": "/Users/chihoyo/Project/CodebaseUnderstanding",
  "file_count_scanned": 12,
  "truncated": false,
  "summary": {
    "edge_count": 77,
    "internal_edge_count": 16,
    "scope_counts": {
      "external": 61,
      "internal": 16
    },
    "language_counts": {
      "python": 77
    }
  },
  "files": [
    "src/codebase_understanding/__init__.py",
    "src/codebase_understanding/cli.py",
    "src/codebase_understanding/import_graph.py",
    "src/codebase_understanding/inventory.py",
    "src/codebase_understanding/pack.py",
    "src/codebase_understanding/render_site.py",
    "src/codebase_understanding/vibe_audit.py",
    "tests/test_import_graph.py",
    "tests/test_inventory.py",
    "tests/test_pack.py",
    "tests/test_render_site.py",
    "tests/test_vibe_audit.py"
  ],
  "edges": [
    {
      "from": "src/codebase_understanding/cli.py",
      "to": null,
      "module": "__future__",
      "kind": "imports",
      "language": "python",
      "scope": "external",
      "line": 3
    },
    {
      "from": "src/codebase_understanding/cli.py",
      "to": null,
      "module": "argparse",
      "kind": "imports",
      "language": "python",
      "scope": "external",
      "line": 5
    },
    {
      "from": "src/codebase_understanding/cli.py",
      "to": null,
      "module": "json",
      "kind": "imports",
      "language": "python",
      "scope": "external",
      "line": 6
    },
    {
      "from": "src/codebase_understanding/cli.py",
      "to": null,
      "module": "shutil",
      "kind": "imports",
      "language": "python",
      "scope": "external",
      "line": 7
    },
    {
      "from": "src/codebase_understanding/cli.py",
      "to": null,
      "module": "sys",
      "kind": "imports",
      "language": "python",
      "scope": "external",
      "line": 8
    },
    {
      "from": "src/codebase_understanding/cli.py",
      "to": null,
      "module": "pathlib",
      "kind": "imports",
      "language": "python",
      "scope": "external",
      "line": 9
    },
    {
      "from": "src/codebase_understanding/cli.py",
      "to": "src/codebase_understanding/__init__.py",
      "module": ".",
      "kind": "imports",
      "language": "python",
      "scope": "internal",
      "line": 11
    },
    {
      "from": "src/codebase_understanding/cli.py",
      "to": "src/codebase_understanding/import_graph.py",
      "module": ".import_graph",
      "kind": "imports",
      "language": "python",
      "scope": "internal",
      "line": 12
    },
    {
      "from": "src/codebase_understanding/cli.py",
      "to": "src/codebase_understanding/inventory.py",
      "module": ".inventory",
      "kind": "imports",
      "language": "python",
      "scope": "internal",
      "line": 13
    },
    {
      "from": "src/codebase_understanding/cli.py",
      "to": "src/codebase_understanding/pack.py",
      "module": ".pack",
      "kind": "imports",
      "language": "python",
      "scope": "internal",
      "line": 14
    },
    {
      "from": "src/codebase_understanding/cli.py",
      "to": "src/codebase_understanding/render_site.py",
      "module": ".render_site",
      "kind": "imports",
      "language": "python",
      "scope": "internal",
      "line": 15
    },
    {
      "from": "src/codebase_understanding/cli.py",
      "to": "src/codebase_understanding/vibe_audit.py",
      "module": ".vibe_audit",
      "kind": "imports",
      "language": "python",
      "scope": "internal",
      "line": 16
    },
    {
      "from": "src/codebase_understanding/import_graph.py",
      "to": null,
      "module": "__future__",
      "kind": "imports",
      "language": "python",
      "scope": "external",
      "line": 3
    },
    {
      "from": "src/codebase_understanding/import_graph.py",
      "to": null,
      "module": "ast",
      "kind": "imports",
      "language": "python",
      "scope": "external",
      "line": 5
    },
    {
      "from": "src/codebase_understanding/import_graph.py",
      "to": null,
      "module": "json",
      "kind": "imports",
      "language": "python",
      "scope": "external",
      "line": 6
    },
    {
      "from": "src/codebase_understanding/import_graph.py",
      "to": null,
      "module": "re",
      "kind": "imports",
      "language": "python",
      "scope": "external",
      "line": 7
    },
    {
      "from": "src/codebase_understanding/import_graph.py",
      "to": null,
      "module": "collections",
      "kind": "imports",
      "language": "python",
      "scope": "external",
      "line": 8
    },
    {
      "from": "src/codebase_understanding/import_graph.py",
      "to": null,
      "module": "pathlib",
      "kind": "imports",
      "language": "python",
      "scope": "external",
      "line": 9
    },
    {
      "from": "src/codebase_understanding/import_graph.py",
      "to": null,
      "module": "typing",
      "kind": "imports",
      "language": "python",
      "scope": "external",
      "line": 10
    },
    {
      "from": "src/codebase_understanding/import_graph.py",
      "to": "src/codebase_understanding/inventory.py",
      "module": ".inventory",
      "kind": "imports",
      "language": "python",
      "scope": "internal",
      "line": 12
    },
    {
      "from": "src/codebase_understanding/inventory.py",
      "to": null,
      "module": "__future__",
      "kind": "imports",
      "language": "python",
      "scope": "external",
      "line": 3
    },
    {
      "from": "src/codebase_understanding/inventory.py",
      "to": null,
      "module": "json",
      "kind": "imports",
      "language": "python",
      "scope": "external",
      "line": 5
    },
    {
      "from": "src/codebase_understanding/inventory.py",
      "to": null,
      "module": "os",
      "kind": "imports",
      "language": "python",
      "scope": "external",
      "line": 6
    },
    {
      "from": "src/codebase_understanding/inventory.py",
      "to": null,
      "module": "collections",
      "kind": "imports",
      "language": "python",
      "scope": "external",
      "line": 7
    },
    {
      "from": "src/codebase_understanding/inventory.py",
      "to": null,
      "module": "pathlib",
      "kind": "imports",
      "language": "python",
      "scope": "external",
      "line": 8
    },
    {
      "from": "src/codebase_understanding/inventory.py",
      "to": null,
      "module": "typing",
      "kind": "imports",
      "language": "python",
      "scope": "external",
      "line": 9
    },
    {
      "from": "src/codebase_understanding/pack.py",
      "to": null,
      "module": "__future__",
      "kind": "imports",
      "language": "python",
      "scope": "external",
      "line": 3
    },
    {
      "from": "src/codebase_understanding/pack.py",
      "to": null,
      "module": "json",
      "kind": "imports",
      "language": "python",
      "scope": "external",
      "line": 5
    },
    {
      "from": "src/codebase_understanding/pack.py",
      "to": null,
      "module": "re",
      "kind": "imports",
      "language": "python",
      "scope": "external",
      "line": 6
    },
    {
      "from": "src/codebase_understanding/pack.py",
      "to": null,
      "module": "datetime",
      "kind": "imports",
      "language": "python",
      "scope": "external",
      "line": 7
    },
    {
      "from": "src/codebase_understanding/pack.py",
      "to": null,
      "module": "pathlib",
      "kind": "imports",
      "language": "python",
      "scope": "external",
      "line": 8
    },
    {
      "from": "src/codebase_understanding/pack.py",
      "to": null,
      "module": "typing",
      "kind": "imports",
      "language": "python",
      "scope": "external",
      "line": 9
    },
    {
      "from": "src/codebase_understanding/pack.py",
      "to": "src/codebase_understanding/import_graph.py",
      "module": ".import_graph",
      "kind": "imports",
      "language": "python",
      "scope": "internal",
      "line": 11
    },
    {
      "from": "src/codebase_understanding/pack.py",
      "to": "src/codebase_understanding/inventory.py",
      "module": ".inventory",
      "kind": "imports",
      "language": "python",
      "scope": "internal",
      "line": 12
    },
    {
      "from": "src/codebase_understanding/pack.py",
      "to": "src/codebase_understanding/vibe_audit.py",
      "module": ".vibe_audit",
      "kind": "imports",
      "language": "python",
      "scope": "internal",
      "line": 13
    },
    {
      "from": "src/codebase_understanding/render_site.py",
      "to": null,
      "module": "__future__",
      "kind": "imports",
      "language": "python",
      "scope": "external",
      "line": 4
    },
    {
      "from": "src/codebase_understanding/render_site.py",
      "to": null,
      "module": "argparse",
      "kind": "imports",
      "language": "python",
      "scope": "external",
      "line": 6
    },
    {
      "from": "src/codebase_understanding/render_site.py",
      "to": null,
      "module": "html",
      "kind": "imports",
      "language": "python",
      "scope": "external",
      "line": 7
    },
    {
      "from": "src/codebase_understanding/render_site.py",
      "to": null,
      "module": "json",
      "kind": "imports",
      "language": "python",
      "scope": "external",
      "line": 8
    },
    {
      "from": "src/codebase_understanding/render_site.py",
      "to": null,
      "module": "re",
      "kind": "imports",
      "language": "python",
      "scope": "external",
      "line": 9
    },
    {
      "from": "src/codebase_understanding/render_site.py",
      "to": null,
      "module": "copy",
      "kind": "imports",
      "language": "python",
      "scope": "external",
      "line": 10
    },
    {
      "from": "src/codebase_understanding/render_site.py",
      "to": null,
      "module": "pathlib",
      "kind": "imports",
      "language": "python",
      "scope": "external",
      "line": 11
    },
    {
      "from": "src/codebase_understanding/render_site.py",
      "to": null,
      "module": "typing",
      "kind": "imports",
      "language": "python",
      "scope": "external",
      "line": 12
    },
    {
      "from": "src/codebase_understanding/vibe_audit.py",
      "to": null,
      "module": "__future__",
      "kind": "imports",
      "language": "python",
      "scope": "external",
      "line": 3
    },
    {
      "from": "src/codebase_understanding/vibe_audit.py",
      "to": null,
      "module": "json",
      "kind": "imports",
      "language": "python",
      "scope": "external",
      "line": 5
    },
    {
      "from": "src/codebase_understanding/vibe_audit.py",
      "to": null,
      "module": "re",
      "kind": "imports",
      "language": "python",
      "scope": "external",
      "line": 6
    },
    {
      "from": "src/codebase_understanding/vibe_audit.py",
      "to": null,
      "module": "collections",
      "kind": "imports",
      "language": "python",
      "scope": "external",
      "line": 7
    },
    {
      "from": "src/codebase_understanding/vibe_audit.py",
      "to": null,
      "module": "pathlib",
      "kind": "imports",
      "language": "python",
      "scope": "external",
      "line": 8
    },
    {
      "from": "src/codebase_understanding/vibe_audit.py",
      "to": null,
      "module": "typing",
      "kind": "imports",
      "language": "python",
      "scope": "external",
      "line": 9
    },
    {
      "from": "src/codebase_understanding/vibe_audit.py",
      "to": "src/codebase_understanding/inventory.py",
      "module": ".inventory",
      "kind": "imports",
      "language": "python",
      "scope": "internal",
      "line": 11
    },
    {
      "from": "tests/test_import_graph.py",
      "to": null,
      "module": "__future__",
      "kind": "imports",
      "language": "python",
      "scope": "external",
      "line": 1
    },
    {
      "from": "tests/test_import_graph.py",
      "to": null,
      "module": "tempfile",
      "kind": "imports",
      "language": "python",
      "scope": "external",
      "line": 3
    },
    {
      "from": "tests/test_import_graph.py",
      "to": null,
      "module": "unittest",
      "kind": "imports",
      "language": "python",
      "scope": "external",
      "line": 4
    },
    {
      "from": "tests/test_import_graph.py",
      "to": null,
      "module": "pathlib",
      "kind": "imports",
      "language": "python",
      "scope": "external",
      "line": 5
    },
    {
      "from": "tests/test_import_graph.py",
      "to": "src/codebase_understanding/import_graph.py",
      "module": "codebase_understanding.import_graph",
      "kind": "imports",
      "language": "python",
      "scope": "internal",
      "line": 7
    },
    {
      "from": "tests/test_inventory.py",
      "to": null,
      "module": "__future__",
      "kind": "imports",
      "language": "python",
      "scope": "external",
      "line": 1
    },
    {
      "from": "tests/test_inventory.py",
      "to": null,
      "module": "tempfile",
      "kind": "imports",
      "language": "python",
      "scope": "external",
      "line": 3
    },
    {
      "from": "tests/test_inventory.py",
      "to": null,
      "module": "unittest",
      "kind": "imports",
      "language": "python",
      "scope": "external",
      "line": 4
    },
    {
      "from": "tests/test_inventory.py",
      "to": null,
      "module": "pathlib",
      "kind": "imports",
      "language": "python",
      "scope": "external",
      "line": 5
    },
    {
      "from": "tests/test_inventory.py",
      "to": "src/codebase_understanding/inventory.py",
      "module": "codebase_understanding.inventory",
      "kind": "imports",
      "language": "python",
      "scope": "internal",
      "line": 7
    },
    {
      "from": "tests/test_pack.py",
      "to": null,
      "module": "__future__",
      "kind": "imports",
      "language": "python",
      "scope": "external",
      "line": 1
    },
    {
      "from": "tests/test_pack.py",
      "to": null,
      "module": "tempfile",
      "kind": "imports",
      "language": "python",
      "scope": "external",
      "line": 3
    },
    {
      "from": "tests/test_pack.py",
      "to": null,
      "module": "unittest",
      "kind": "imports",
      "language": "python",
      "scope": "external",
      "line": 4
    },
    {
      "from": "tests/test_pack.py",
      "to": null,
      "module": "pathlib",
      "kind": "imports",
      "language": "python",
      "scope": "external",
      "line": 5
    },
    {
      "from": "tests/test_pack.py",
      "to": "src/codebase_understanding/pack.py",
      "module": "codebase_understanding.pack",
      "kind": "imports",
      "language": "python",
      "scope": "internal",
      "line": 7
    },
    {
      "from": "tests/test_render_site.py",
      "to": null,
      "module": "__future__",
      "kind": "imports",
      "language": "python",
      "scope": "external",
      "line": 1
    },
    {
      "from": "tests/test_render_site.py",
      "to": null,
      "module": "json",
      "kind": "imports",
      "language": "python",
      "scope": "external",
      "line": 3
    },
    {
      "from": "tests/test_render_site.py",
      "to": null,
      "module": "tempfile",
      "kind": "imports",
      "language": "python",
      "scope": "external",
      "line": 4
    },
    {
      "from": "tests/test_render_site.py",
      "to": null,
      "module": "unittest",
      "kind": "imports",
      "language": "python",
      "scope": "external",
      "line": 5
    },
    {
      "from": "tests/test_render_site.py",
      "to": null,
      "module": "pathlib",
      "kind": "imports",
      "language": "python",
      "scope": "external",
      "line": 6
    },
    {
      "from": "tests/test_render_site.py",
      "to": "src/codebase_understanding/render_site.py",
      "module": "codebase_understanding.render_site",
      "kind": "imports",
      "language": "python",
      "scope": "internal",
      "line": 8
    },
    {
      "from": "tests/test_vibe_audit.py",
      "to": null,
      "module": "__future__",
      "kind": "imports",
      "language": "python",
      "scope": "external",
      "line": 1
    },
    {
      "from": "tests/test_vibe_audit.py",
      "to": null,
      "module": "json",
      "kind": "imports",
      "language": "python",
      "scope": "external",
      "line": 3
    },
    {
      "from": "tests/test_vibe_audit.py",
      "to": null,
      "module": "tempfile",
      "kind": "imports",
      "language": "python",
      "scope": "external",
      "line": 4
    },
    {
      "from": "tests/test_vibe_audit.py",
      "to": null,
      "module": "unittest",
      "kind": "imports",
      "language": "python",
      "scope": "external",
      "line": 5
    },
    {
      "from": "tests/test_vibe_audit.py",
      "to": null,
      "module": "pathlib",
      "kind": "imports",
      "language": "python",
      "scope": "external",
      "line": 6
    },
    {
      "from": "tests/test_vibe_audit.py",
      "to": "src/codebase_understanding/vibe_audit.py",
      "module": "codebase_understanding.vibe_audit",
      "kind": "imports",
      "language": "python",
      "scope": "internal",
      "line": 8
    }
  ]
}
